<recipe>

  <id>21</id>

  <title>G&#259;lu&#351;te de ficat pentru supe</title>

  <ingredients>
    <item>300 g ficat</item>
    <item>1 ou</item>
    <item>1 felie franzel&#259;</item>
    <item>sare</item>
    <item>piper</item>
  </ingredients>

  <preparation>
Se cur&#259;&#355;&#259; ficatul de pieli&#355;e &#351;i se pune s&#259; fiarb&#259;. Apoi se d&#259; prin ma&#351;ina de tocat &#238;mpreun&#259; cu miezul de p&#238;ine muiat &#238;n ap&#259; &#351;i stors. Se adaug&#259; oul, pu&#355;in&#259; sare &#351;i pu&#355;in piper, &#351;i se amestec&#259; bine.  Se modeleaz&#259; g&#259;lu&#351;te de m&#259;rimea unei prune &#351;i se pun &#238;n sup&#259; s&#259; fiarb&#259;.
  </preparation>

</recipe>
