<recipe>

  <id>18</id>

  <title>Sup&#259; de oase cu zdren&#355;e</title>

  <ingredients>
    <item>1 litru sup&#259; de oase</item>
    <item>2 ou&#259;</item>
    <item>sare</item>
    <item>p&#259;trunjel verde tocat</item>
    <item>1 lingur&#259; f&#259;in&#259; (20 g)</item>
  </ingredients>

  <preparation>
Se pune supa de oase la fiert, la foc mic. C&#226;nd &#238;ncepe s&#259; fiarb&#259;, se bat ou&#259;le, se amestec&#259; cu f&#259;in&#259; ca s&#259; dea un aluat ca de cl&#259;tite &#351;i se d&#259; drumul &#238;n sup&#259;, folosind lingura din care aluatul s&#259; cad&#259; sub form&#259; de pic&#259;turi. Se las&#259; s&#259; fiarb&#259; p&#226;n&#259; se &#238;ncheag&#259;. Se adaug&#259; p&#259;trunjel verde tocat. Se serve&#351;te. Se pot ad&#259;uga g&#259;lu&#351;te de carne. Vezi re&#355;eta "G&#259;lu&#351;te de carne".
  </preparation>

</recipe>
