<recipe>

  <id>16</id>

  <title>Sos pentru pe&#351;te</title>

  <ingredients>
    <item>3 g&#259;lbenu&#351;uri fierte tari</item>
    <item>4 linguri (80 g) cu untdelemn</item>
    <item>1 lingur&#259; ras&#259; cu mu&#351;tar</item>
    <item>3 linguri o&#355;et slab</item>
    <item>pu&#355;in&#259; ceap&#259; ras&#259;</item>
    <item>piper</item>
    <item>sare</item>
  </ingredients>

  <preparation>
Se amestec&#259; bine g&#259;lbenu&#351;urile date prin sit&#259; cu untdelemn, pus c&#238;te pu&#355;in, apoi se adaug&#259; mu&#351;tarul, o&#355;etul, ceapa ras&#259;, sare si piper &#351;i se freac&#259; bine p&#238;n&#259; se &#238;ngroa&#351;&#259;; dac&#259; este prea gros se pune pu&#355;in&#259; zeam&#259; &#238;n care a fiert pe&#351;tele. Se d&#259; la rece.  Se serve&#351;te la pe&#351;te.
  </preparation>

</recipe>
