<recipe>

  <id>62</id>

  <title>Ficat de g&#238;sc&#259; la gr&#259;tar</title>

  <ingredients>
    <item>1-2 fica&#355;i de g&#238;sc&#259;</item>
    <item>1/2 lingur&#259; gr&#259;sime de g&#238;sc&#259; sau unt</item>
    <item>sare</item>
    <item>piper</item>
  </ingredients>

  <preparation>
Se spal&#259; ficatul, se cur&#259;&#355;&#259; de pieli&#355;e, se taie felii mai groase pe orizontal&#259;, se pip&#259;reaz&#259; &#351;i se a&#351;eaz&#259; pe un gr&#259;tar uns cu unt. Se pune gr&#259;tarul pe jar domol p&#238;n&#259; c&#238;nd ficatul este bine p&#259;truns &#351;i nu mai las&#259; s&#238;nge. C&#238;nd este gata se s&#259;reaz&#259; dup&#259; gust.
  </preparation>

</recipe>
