<recipe>

  <id>90</id>

  <title>Pot&#238;rnichea cu sm&#238;nt&#238;n&#259;</title>

  <ingredients>
    <item>1 pot&#238;rniche</item>
    <item>c&#238;teva felii de sl&#259;nin&#259;</item>
    <item>1/2 lingur&#259; unt (15 g)</item>
    <item>1 lingur&#259; sm&#238;nt&#238;n&#259; (25 g)</item>
    <item>sare</item>
    <item>piper</item>
  </ingredients>

  <preparation>
Se cur&#259;&#355;&#259; pot&#238;rnichea, se spal&#259;, se &#238;nvele&#351;te &#238;n felii de sl&#259;nin&#259; &#351;i se frige &#238;n unt. Pot&#238;rnichea se a&#351;eaz&#259; pe spate ca s&#259; nu se ard&#259; carnea de pe piept. Dup&#259; ce s-a fript, se scoate sl&#259;nina &#351;i se a&#351;eaz&#259; pas&#259;rea pe o farfurie cu sosul &#238;n care s-a fript. Se toarn&#259; sm&#238;nt&#238;n&#259; peste pot&#238;rniche &#351;i se serve&#351;te.
  </preparation>

</recipe>
