<recipe>

  <id>32</id>

  <title>Ghiveci pentru iarn&#259;</title>

  <ingredients>
    <item>5 kg ro&#351;ii</item>
    <item>1,500 kg fasole verde t&#238;n&#259;r&#259;</item>
    <item>1 kg bame</item>
    <item>1 kg arpagic</item>
    <item>2-3 cepe de ap&#259;</item>
    <item>15 ardei gra&#351;i</item>
    <item>6 ardei cornul caprei</item>
    <item>6 morcovi</item>
    <item>3 p&#259;st&#238;rnaci</item>
    <item>2 p&#259;trunjei</item>
    <item>2 &#355;eline</item>
    <item>10 vinete</item>
    <item>10 dovlecei</item>
    <item>2 c&#259;&#355;ei usturoi</item>
  </ingredients>

  <preparation>
Se spal&#259;, se cur&#259;&#355;&#259; &#351;i se taie felii legumele. Se prepar&#259; suc de ro&#351;ii din 5 kg ro&#351;ii date prin ma&#351;in&#259;. Se pun legumele, f&#259;r&#259; vinete &#351;i dovlecei, &#238;n suc de ro&#351;ii, se las&#259; s&#259; fiarb&#259; o or&#259;, se adaug&#259; vinetele cur&#259;&#355;ate &#351;i t&#259;iate cuburi, s&#259;rate &#351;i bine stoarse, apoi dovleceii &#351;i se fierbe &#238;nc&#259; 1/2 or&#259;. Se pun doi c&#259;&#355;ei de usturoi, dou&#259; foi de dafin, 10 boabe de piper, 0,500 l untdelemn, sare, p&#259;trunjel verde, foi de &#355;elin&#259; &#351;i se mai fierb 10 minute. Se las&#259; s&#259; se r&#259;ceasc&#259;, se pune &#238;n borcane &#351;i deasupra pu&#355;in, acid salicilic. Se leag&#259; foarte bine cu celofan, apoi cu o c&#238;rp&#259; &#351;i se fierbe o or&#259; &#238;n baie de ap&#259;.
  </preparation>

</recipe>
/preparation>

</recipe>
