<recipe>

  <id>26</id>

  <title>Sos picant pentru iarn&#259;</title>

  <ingredients>
    <item>6 kg ro&#351;ii</item>
    <item>250 g zah&#259;r</item>
    <item>2 linguri&#355;e piper</item>
    <item>sare</item>
    <item>2 linguri mu&#351;tar dizolvat &#238;ntr-un pahar cu o&#355;et</item>
  </ingredients>

  <preparation>
Se spal&#259; ro&#351;iile, se rup buc&#259;&#355;i, se pun la fiert, se dau prin sit&#259; &#351;i se pune din nou la fiert p&#238;n&#259; devine un bulion. Se adaug&#259; zah&#259;rul, mu&#351;tarul, piperul, sarea &#351;i se amestec&#259; totul. Se pune apoi &#238;n sticle, se leag&#259; cu celofan si se fierb &#238;n baie de ap&#259; jum&#259;tate de or&#259;. Se ia de pe foc &#351;i se las&#259; vasul a&#351;a cu tot cu sticle p&#238;n&#259; se r&#259;ce&#351;te.  Se dau la c&#259;mar&#259;. Se serve&#351;te la fripturi.
  </preparation>

</recipe>
ion>

</recipe>
