<recipe>

  <id>21</id>

  <title>Salata de vinete</title>

  <ingredients>
    <item>3 vinete</item>
    <item>un pahar cu untdelemn</item>
    <item>o ceap&#259; mai mic&#259;</item>
    <item>sare</item>
    <item>ro&#351;ii &#351;i ardei gra&#351;i pentru garnisit</item>
  </ingredients>

  <preparation>
Se aleg vinete tinere &#351;i sub&#355;iri s&#259; nu con&#355;in&#259; semin&#355;e multe. Se coc direct pe flac&#259;r&#259; de la aragaz sau pe c&#259;rbunii de la lemne sau pe plit&#259;. Vinetele se &#238;ntorc pe foc ca s&#259; se coac&#259; bine peste tot. C&#238;nd s-au &#238;nmuiat bine, s&#238;nt gata. Imediat se pun pe un fund de lemn &#351;i numai dou&#259; minute se &#355;in acoperite cu un &#351;ervet ca s&#259; transpire bine &#351;i s&#259; se cure&#355;e numai coaja neagr&#259;. Apoi se iau de codi&#355;&#259; &#351;l se &#238;ndep&#259;rteaz&#259; u&#351;or coaja neagr&#259;, sp&#259;l&#238;nd degetele sub jet de apa. Se taie cu lingura de lemn cotorul, se pun pe fundul de lemn &#351;i se toac&#259; foarte bine cu un cu&#355;it de lemn. Dup&#259; ce s-au tocat foarte bine, se pun &#238;ntr-un castron de por&#355;elan &#351;i se bat bine cu untdelemn pus &#238;n rate &#351;i amestecat bine. Se pune sare &#351;i ceap&#259; tocat&#259; foarte m&#259;runt. Untdelemnul se pune c&#238;nd s&#238;nt vinetele calde &#238;nc&#259;, pentru c&#259; numai atunci absoarbe bine uleiul &#351;i vor r&#259;m&#238;ne albe &#351;i gustoase.  Se garnisesc frumos cu felii de ro&#351;ii &#351;i ardei gra&#351;i. Nu se folosesc linguri de metal, nu se &#355;in &#238;n vase cu smal&#355;ul c&#259;zut. Dac&#259; vinetele nu s-au tocat imediat &#351;i s-au l&#259;sat s&#259; stea mai mult se &#238;nnegresc. Ca s&#259; dispar&#259; negreala se amestec&#259; &#238;n ele un g&#259;lbenu&#351; de ou crud &#351;i se bat bine cu ulei p&#238;n&#259; se albesc.
  </preparation>

</recipe>
