<recipe>

  <id>65</id>

  <title>Fica&#355;i de p&#259;s&#259;ri &#238;n sos</title>

  <ingredients>
    <item>Fica&#355;i de la diferite p&#259;s&#259;ri</item>
    <item>zeama de l&#259;m&#238;ie</item>
    <item>untdelemn</item>
    <item>pesmet</item>
    <item>1-2 c&#259;&#355;ei usturoi</item>
    <item>p&#259;trunjel verde</item>
  </ingredients>

  <preparation>
Se pr&#259;jesc fica&#355;ii &#238;n untdelemn, f&#259;r&#259; sare. C&#238;nd s-au rumenit se scot pe o farfurie.  Se prepar&#259; un sos din untdelemnul &#238;n care s-au pr&#259;jit fica&#355;ii &#351;i &#238;n care se adaug&#259; zeam&#259; de l&#259;m&#238;ie, pu&#355;in pesmet, usturoi tocat &#351;i se amestec&#259; pe foc p&#238;n&#259; se leag&#259;.  &#238;n acest sos se pun fica&#355;ii &#351;i p&#259;trunjel verde tocat. Se las&#259; s&#259; musteasc&#259; pu&#355;in la foc mic, apoi se servesc.
  </preparation>

</recipe>
