<recipe>

  <id>44</id>

  <title>Chiftelu&#355;e dietetice fierte &#238;n aburi</title>

  <ingredients>
    <item>500 g carne</item>
    <item>1 felie franzel&#259;</item>
    <item>1/2 cea&#351;c&#259; lapte</item>
    <item>sare</item>
    <item>1 ou</item>
  </ingredients>

  <preparation>
Se d&#259; carnea &#351;i p&#238;inea &#238;nmuiat&#259; &#238;n lapte &#351;i stoars&#259; prin ma&#351;in&#259; &#351;i se amestec&#259; cu ou, sare &#351;i o lingur&#259; de untdelemn; se fr&#259;m&#238;nt&#259; bine &#351;i se fac chiftelu&#355;e care se fierb &#238;n aburi. Se a&#351;eaz&#259; chiftelu&#355;ele pe o sit&#259; care se pune pe o oal&#259; cu ap&#259; care fierbe, dar sita s&#259; nu ating&#259; apa, ci numai aburii care trec prin sit&#259; s&#259; fiarb&#259; chiftelu&#355;ele, Se servesc cu soteuri.
  </preparation>

</recipe>
